{"stat.walkOneCm":411065,"stat.leaveGame":4,"stat.drop.minecraft.gunpowder":5,"stat.drop.minecraft.bone":1,"stat.drop.minecraft.golden_apple":4,"stat.mobKills":2,"stat.killEntity.Creeper":2,"stat.drop.minecraft.spawn_egg":5,"stat.pickup.minecraft.spawn_egg":5,"stat.flyOneCm":1733186,"stat.drop":15,"stat.jump":202,"stat.playOneMinute":4163,"stat.drop.minecraft.wheat_seeds":1,"stat.damageDealt":381,"stat.pickup.minecraft.gunpowder":4,"stat.useItem.minecraft.wool":64,"stat.timeSinceDeath":4163,"stat.useItem.minecraft.spawn_egg":5}